iotile_support_firm_accelerometer_2/__init__.py
iotile_support_firm_accelerometer_2/accel1_1.py
iotile_support_firm_accelerometer_2/accel1_proxy.py
iotile_support_firm_accelerometer_2/dev_accel1_1.py
iotile_support_firm_accelerometer_2/common/__init__.py
iotile_support_firm_accelerometer_2/common/constants.py
iotile_support_firm_accelerometer_2/common/heatshrink.py
iotile_support_firm_accelerometer_2/common/utilities.py
iotile_support_firm_accelerometer_2/common/waveforms.py
iotile_support_firm_accelerometer_2/emulator/__init__.py
iotile_support_firm_accelerometer_2/emulator/state.py
iotile_support_firm_accelerometer_2/model/__init__.py
iotile_support_firm_accelerometer_2/model/accel_model.py
iotile_support_firm_accelerometer_2-2.4.4.dist-info/METADATA
iotile_support_firm_accelerometer_2-2.4.4.dist-info/WHEEL
iotile_support_firm_accelerometer_2-2.4.4.dist-info/entry_points.txt
iotile_support_firm_accelerometer_2-2.4.4.dist-info/top_level.txt
iotile_support_firm_accelerometer_2-2.4.4.dist-info/RECORD
