Metadata-Version: 2.1
Name: iotile-support-firm-accelerometer-2
Version: 2.4.4
Summary: UNKNOWN
Home-page: UNKNOWN
Author: Arch
Author-email: info@arch-iot.com
License: UNKNOWN
Platform: UNKNOWN
Requires-Dist: bitstring (~=3.1)
Requires-Dist: iotile-core (~=5.0)
